[
    {
		"schemes": [
			{
				"in": true,
				"scheme": {
                    "type": "object",
                    "properties": {
                        "a": {
                            "type": "string"
                        }
                    },
                    "required": ["a"]
                },
				"type": "json-schema"
			}
		],
		"usage": {
			"name": "user",
            "address": [],
            "check_url": "http://localhost:8882/usage.json"
		}
    },
    {
		"schemes": [
			{
				"in": true,
				"scheme": {
                    "type": "object",
                    "properties": {
                        "b": {
                            "type": "string"
                        }
                    }
                },
				"type": "json-schema"
			}
		],
		"usage": {
			"name": "user",
            "address": [],
            "check_url": "http://localhost:8882/usage.json"
		}
	}
]
